keg/Dataset.py
keg/Schema.py
keg/__init__.py
spr_keg-0.0.1.dist-info/METADATA
spr_keg-0.0.1.dist-info/WHEEL
spr_keg-0.0.1.dist-info/top_level.txt
spr_keg-0.0.1.dist-info/RECORD
