Metadata-Version: 2.1
Name: spr-keg
Version: 0.0.1
Summary: Keg of utilitites to be installed in worker nodes.
Home-page: https://github.com/spraoi/keg
Author: Ravi N
Author-email: ravi@spraoi.ai
License: MIT
Platform: UNKNOWN
Classifier: License :: OSI Approved :: MIT License
Classifier: Programming Language :: Python
Classifier: Programming Language :: Python :: 3
Classifier: Programming Language :: Python :: 3.7
Classifier: Programming Language :: Python :: Implementation :: CPython
Classifier: Programming Language :: Python :: Implementation :: PyPy
Requires-Python: >=3.7.0
Requires-Dist: requests
Requires-Dist: pandas
Requires-Dist: records
